adityas_fsscan-1.0.dist-info/licenses/LICENSE
src/__init__.py
src/count_data.py
src/file_scanner.py
src/main.py
adityas_fsscan-1.0.dist-info/METADATA
adityas_fsscan-1.0.dist-info/WHEEL
adityas_fsscan-1.0.dist-info/entry_points.txt
adityas_fsscan-1.0.dist-info/top_level.txt
adityas_fsscan-1.0.dist-info/RECORD
