Metadata-Version: 2.4
Name: adityas-fsscan
Version: 1.0
License-File: LICENSE
Dynamic: description
Dynamic: description-content-type
Dynamic: license-file
